{
    "Ar36": {
        "error": 0.0008470992843958921,
        "error_type": "SEM",
        "filter_outliers_dict": {
            "filter_outliers": true,
            "iterations": 1,
            "std_devs": 2
        },
        "fit": "linear",
        "value": 0.31792230577293823
    },
    "Ar37": {
        "error": 0.0035993790088437805,
        "error_type": "SEM",
        "filter_outliers_dict": {
            "filter_outliers": true,
            "iterations": 1,
            "std_devs": 2
        },
        "fit": "linear",
        "value": -0.017440501444629383
    },
    "Ar38": {
        "error": 0.0032005981757268465,
        "error_type": "SEM",
        "filter_outliers_dict": {
            "filter_outliers": true,
            "iterations": 1,
            "std_devs": 2
        },
        "fit": "linear",
        "value": 0.1393647953796016
    },
    "Ar39": {
        "error": 0.011911643802145233,
        "error_type": "SEM",
        "filter_outliers_dict": {
            "filter_outliers": true,
            "iterations": 1,
            "std_devs": 2
        },
        "fit": "parabolic",
        "value": 0.08330920514690066
    },
    "Ar40": {
        "error": 0.022077604735709307,
        "error_type": "SEM",
        "filter_outliers_dict": {
            "filter_outliers": true,
            "iterations": 1,
            "std_devs": 3
        },
        "fit": "parabolic",
        "value": 92.73073882963388
    },
    "Ar41": {
        "error": 0.01875193453605437,
        "error_type": "SEM",
        "filter_outliers_dict": {
            "filter_outliers": true,
            "iterations": 1,
            "std_devs": 3
        },
        "fit": "average",
        "value": -0.24128187087393327
    }
}