{
    "AX": {
        "error": 0.007794585339476053,
        "error_type": "SEM",
        "filter_outliers_dict": {
            "filter_outliers": true,
            "iterations": 1,
            "std_devs": 3,
            "use_iqr_filtering": false,
            "use_standard_deviation_filtering": false
        },
        "fit": "average",
        "fn": 45,
        "include_baseline_error": false,
        "n": 45,
        "outlier_excluded": [],
        "reviewed": true,
        "user_excluded": [],
        "value": -0.030916571855131122
    },
    "CDD": {
        "error": 5.817085382038789e-06,
        "error_type": "SEM",
        "filter_outliers_dict": {
            "filter_outliers": true,
            "iterations": 1,
            "std_devs": 10,
            "use_iqr_filtering": false,
            "use_standard_deviation_filtering": false
        },
        "fit": "average",
        "fn": 45,
        "include_baseline_error": false,
        "n": 45,
        "outlier_excluded": [],
        "reviewed": true,
        "user_excluded": [],
        "value": 1.0312590165995062e-05
    },
    "H1": {
        "error": 0.0060248831993544505,
        "error_type": "SEM",
        "filter_outliers_dict": {
            "filter_outliers": true,
            "iterations": 1,
            "std_devs": 3,
            "use_iqr_filtering": false,
            "use_standard_deviation_filtering": false
        },
        "fit": "average",
        "fn": 44,
        "include_baseline_error": false,
        "n": 45,
        "outlier_excluded": [
            43
        ],
        "reviewed": true,
        "user_excluded": [],
        "value": 0.007412308686815033
    },
    "H2": {
        "error": 0.03619823042722656,
        "error_type": "SEM",
        "filter_outliers_dict": {
            "filter_outliers": true,
            "iterations": 1,
            "std_devs": 3,
            "use_iqr_filtering": false,
            "use_standard_deviation_filtering": false
        },
        "fit": "average",
        "fn": 44,
        "include_baseline_error": false,
        "n": 45,
        "outlier_excluded": [
            14
        ],
        "reviewed": true,
        "user_excluded": [],
        "value": -0.22161604114808142
    },
    "L1": {
        "error": 0.00417119565339149,
        "error_type": "SEM",
        "filter_outliers_dict": {
            "filter_outliers": true,
            "iterations": 1,
            "std_devs": 3,
            "use_iqr_filtering": false,
            "use_standard_deviation_filtering": false
        },
        "fit": "average",
        "fn": 45,
        "include_baseline_error": false,
        "n": 45,
        "outlier_excluded": [],
        "reviewed": true,
        "user_excluded": [],
        "value": 0.040665950331216054
    },
    "L2": {
        "error": 0.004842015314681735,
        "error_type": "SEM",
        "filter_outliers_dict": {
            "filter_outliers": true,
            "iterations": 1,
            "std_devs": 3
        },
        "fit": "average",
        "value": -0.04937803039259065
    }
}