{
    "Ar36": {
        "error": 0.002172979216361696,
        "error_type": "SEM",
        "filter_outliers_dict": {
            "filter_outliers": true,
            "iterations": 1,
            "std_devs": 2
        },
        "fit": "linear",
        "value": 1.2779231568804486
    },
    "Ar37": {
        "error": 0.005549362907254529,
        "error_type": "SEM",
        "filter_outliers_dict": {
            "filter_outliers": true,
            "iterations": 1,
            "std_devs": 2
        },
        "fit": "linear",
        "value": 0.01000290287072975
    },
    "Ar38": {
        "error": 0.004148658945431756,
        "error_type": "SEM",
        "filter_outliers_dict": {
            "filter_outliers": true,
            "iterations": 1,
            "std_devs": 2
        },
        "fit": "linear",
        "value": 0.3222645629408732
    },
    "Ar39": {
        "error": 0.018494607115814066,
        "error_type": "SEM",
        "filter_outliers_dict": {
            "filter_outliers": true,
            "iterations": 1,
            "std_devs": 2
        },
        "fit": "parabolic",
        "value": 0.06270630135291785
    },
    "Ar40": {
        "error": 0.06159465232934739,
        "error_type": "SEM",
        "filter_outliers_dict": {
            "filter_outliers": true,
            "iterations": 1,
            "std_devs": 3
        },
        "fit": "parabolic",
        "value": 376.2614969829361
    },
    "Ar41": {
        "error": 0.022290424724328926,
        "error_type": "SEM",
        "filter_outliers_dict": {
            "filter_outliers": true,
            "iterations": 1,
            "std_devs": 3
        },
        "fit": "average",
        "value": -0.11806361171662927
    }
}